.gitignore
.pre-commit-config.yaml
LICENSE.md
README.md
mkdocs.yml
pyproject.toml
setup.py
.github/workflows/ci.yml
docs/override/main.html
docs/source/.pages
docs/source/CNAME
docs/source/index.md
docs/source/benchmark/index.md
docs/source/benchmark/diff/models.py
docs/source/benchmark/diff/simulated.py
docs/source/benchmark/diff/timing.py
docs/source/javascripts/reference.js
docs/source/quickstart/0_install.py
docs/source/quickstart/1_data.py
docs/source/quickstart/2_diff.py
docs/source/quickstart/3_pred.py
docs/source/reference/.pages
docs/source/reference/index.md
docs/source/reference/data/clustering.md
docs/source/reference/data/folds.md
docs/source/reference/data/fragments.md
docs/source/reference/data/motifscan.md
docs/source/reference/data/regions.md
docs/source/reference/data/transcriptome.md
docs/source/reference/loaders/fragments.md
docs/source/reference/models/diff/interpret.md
docs/source/reference/models/diff/model.md
docs/source/reference/models/diff/plot.md
docs/source/reference/models/pred/interpret.md
docs/source/reference/models/pred/model.md
docs/source/reference/models/pred/plot.md
docs/source/static/comparison.gif
docs/source/static/eu.png
docs/source/static/favicon.ai
docs/source/static/favicon.png
docs/source/static/logo.ai
docs/source/static/logo.png
docs/source/static/models/diff/logo.pdf
docs/source/static/models/diff/1x/logo.png
docs/source/static/models/dime/logo.pdf
docs/source/static/models/dime/logo.png
docs/source/static/models/pred/logo.pdf
docs/source/static/models/pred/1x/logo.png
docs/source/static/models/time/logo.pdf
docs/source/static/models/time/logo.png
docs/source/stylesheets/extra-reference.css
docs/source/stylesheets/extra.css
docs/tex/overview.tex
scripts/cythonize.sh
scripts/dist.sh
scripts/docs.sh
scripts/install.sh
scripts/test.py
scripts/benchmark/datasets/pbmc10k/1-download.py
scripts/benchmark/datasets/pbmc10k/2-process_all.py
scripts/benchmark/datasets/pbmc10k/3-process_large.py
src/chromatinhd.egg-info/PKG-INFO
src/chromatinhd.egg-info/SOURCES.txt
src/chromatinhd.egg-info/dependency_links.txt
src/chromatinhd.egg-info/requires.txt
src/chromatinhd.egg-info/top_level.txt
