Metadata-Version: 2.1
Name: chromatinhd
Version: 0.3.12
Summary: High-definition modeling of (single-cell) chromatin + transcriptomics data
Author-email: Wouter Saelens <wouter.saelens@gmail.com>
License: MIT
Project-URL: Homepage, https://github.com/DeplanckeLab/ChromatinHD
Project-URL: Bug Tracker, https://github.com/DeplanckeLab/ChromatinHD/issues
Keywords: bioinformatics,chromatin accessibility,transcriptomics
Classifier: Programming Language :: Python :: 3
Requires-Python: >=3.8
License-File: LICENSE.md
Requires-Dist: torch
Requires-Dist: scanpy
Requires-Dist: matplotlib
Requires-Dist: numpy
Requires-Dist: seaborn
Requires-Dist: diskcache
Requires-Dist: appdirs
Requires-Dist: xarray
Requires-Dist: requests
Requires-Dist: zarr
Requires-Dist: pathlibfs
Provides-Extra: sam
Requires-Dist: pysam; extra == "sam"
Provides-Extra: dev
Requires-Dist: pre-commit; extra == "dev"
Requires-Dist: pytest; extra == "dev"
Requires-Dist: coverage; extra == "dev"
Requires-Dist: polyptich; extra == "dev"
Requires-Dist: black; extra == "dev"
Requires-Dist: pylint; extra == "dev"
Requires-Dist: jupytext; extra == "dev"
Requires-Dist: mkdocs; extra == "dev"
Requires-Dist: mkdocs-material; extra == "dev"
Requires-Dist: mkdocstrings[python]; extra == "dev"
Requires-Dist: mkdocs-jupyter; extra == "dev"
Requires-Dist: mike; extra == "dev"
Requires-Dist: cairosvg; extra == "dev"
Requires-Dist: pillow; extra == "dev"
Requires-Dist: mkdocs-awesome-pages-plugin; extra == "dev"
Requires-Dist: setuptools_scm; extra == "dev"
Requires-Dist: Cython; extra == "dev"
Provides-Extra: test
Requires-Dist: pytest; extra == "test"
Requires-Dist: ruff; extra == "test"
Provides-Extra: full
Requires-Dist: chromatinhd[sam]; extra == "full"
